naver_search/__init__.py
naver_search/error.py
naver_search/model.py
naver_search/naver.py
naver_search/naverconver.py
naver_search-3.0.0.dist-info/METADATA
naver_search-3.0.0.dist-info/WHEEL
naver_search-3.0.0.dist-info/top_level.txt
naver_search-3.0.0.dist-info/RECORD
